positionkey/__init__.py
positionkey/__main__.py
positionkey/config.txt
positionkey-1.1.2.dist-info/LICENSE
positionkey-1.1.2.dist-info/METADATA
positionkey-1.1.2.dist-info/WHEEL
positionkey-1.1.2.dist-info/top_level.txt
positionkey-1.1.2.dist-info/RECORD
