Metadata-Version: 2.1
Name: positionkey
Version: 1.1.2
Summary: A multi-platform python package for mdapping key strokes to mouse clicks.
Author-email: Nitesh Prasad <nitesh1612@gmail.com>
License: MIT License
Project-URL: Documentation, https://github.com/niteshctrl/positionkey/blob/main/README.md
Project-URL: Repository, https://github.com/niteshctrl/positionkey/
Project-URL: Issues, https://github.com/niteshctrl/positionkey/issues
Keywords: tdac,keyboard shortcut,annotation,labelling
Classifier: Development Status :: 5 - Production/Stable
Classifier: Programming Language :: Python :: 3
Classifier: License :: OSI Approved :: MIT License
Classifier: Operating System :: OS Independent
Requires-Python: >=3.6
License-File: LICENSE
Requires-Dist: pyautogui ==0.9.53
Requires-Dist: pynput ==1.6.7
